rfc_cli/__init__.py
rfc_cli/__main__.py
rfc_cli/core.py
rfc_cli-1.0.0.dist-info/LICENSE
rfc_cli-1.0.0.dist-info/METADATA
rfc_cli-1.0.0.dist-info/WHEEL
rfc_cli-1.0.0.dist-info/entry_points.txt
rfc_cli-1.0.0.dist-info/top_level.txt
rfc_cli-1.0.0.dist-info/RECORD
